collectives/__init__.py
collectives-0.0.1.dist-info/METADATA
collectives-0.0.1.dist-info/WHEEL
collectives-0.0.1.dist-info/top_level.txt
collectives-0.0.1.dist-info/RECORD
